LICENSE
MANIFEST.in
README.md
setup.py
pyradium/Acrofile.py
pyradium/Acronyms.py
pyradium/ActionAcroAdd.py
pyradium/ActionAcroScan.py
pyradium/ActionAcroSort.py
pyradium/ActionAcroTex.py
pyradium/ActionDictAdd.py
pyradium/ActionDumpMetadata.py
pyradium/ActionHashPresentation.py
pyradium/ActionModify.py
pyradium/ActionPurge.py
pyradium/ActionRender.py
pyradium/ActionServe.py
pyradium/ActionShowStyleOpts.py
pyradium/ActionSpellcheck.py
pyradium/ActionStandalone.py
pyradium/ActionTemplateHelper.py
pyradium/Agenda.py
pyradium/BaseAction.py
pyradium/BaseDirective.py
pyradium/BooleanExpression.py
pyradium/CircuitJS.py
pyradium/CmdlineEscape.py
pyradium/CmdlineParser.py
pyradium/Controller.py
pyradium/Deployment.py
pyradium/DigitalTimingDiagram.py
pyradium/Enums.py
pyradium/Exceptions.py
pyradium/ExtendedJSONEncoder.py
pyradium/FileLookup.py
pyradium/FriendlyArgumentParser.py
pyradium/GenericTOC.py
pyradium/GlobalConfig.py
pyradium/Logging.py
pyradium/Markers.py
pyradium/MultiCommand.py
pyradium/OrderedSet.py
pyradium/PauseRenderer.py
pyradium/PrefixMatcher.py
pyradium/Presentation.py
pyradium/RenderableSlide.py
pyradium/RenderedPresentation.py
pyradium/Renderer.py
pyradium/RendererCache.py
pyradium/RenderingParameters.py
pyradium/Schedule.py
pyradium/Slide.py
pyradium/Spellcheck.py
pyradium/SpellcheckDictionary.py
pyradium/StyleParameters.py
pyradium/TOC.py
pyradium/Tools.py
pyradium/VariableSubstitution.py
pyradium/__init__.py
pyradium/__main__.py
pyradium.egg-info/PKG-INFO
pyradium.egg-info/SOURCES.txt
pyradium.egg-info/dependency_links.txt
pyradium.egg-info/entry_points.txt
pyradium.egg-info/requires.txt
pyradium.egg-info/top_level.txt
pyradium/modify/BaseModifyCommand.py
pyradium/modify/CircuitJSRenderImages.py
pyradium/modify/__init__.py
pyradium/renderer/BaseRenderer.py
pyradium/renderer/DigitalTimingDiagramRenderer.py
pyradium/renderer/ExecRenderer.py
pyradium/renderer/GraphvizRenderer.py
pyradium/renderer/ImageRenderer.py
pyradium/renderer/LatexFormulaRenderer.py
pyradium/renderer/PlotRenderer.py
pyradium/renderer/QRCodeRenderer.py
pyradium/renderer/__init__.py
pyradium/scripts/Helper.py
pyradium/scripts/__init__.py
