Metadata-Version: 2.1
Name: pyradium
Version: 0.0.17
Summary: Creating HTML presentations with LaTeX-ish features from XML source
Home-page: https://github.com/johndoe31415/pyradium
Download-URL: https://github.com/johndoe31415/pyradium/archive/0.0.17.tar.gz
Author: Johannes Bauer
Author-email: joe@johannes-bauer.com
License: gpl-3.0
Keywords: latex,presentation,template,html
Classifier: Development Status :: 5 - Production/Stable
Classifier: Intended Audience :: Developers
Classifier: License :: OSI Approved :: GNU General Public License v3 (GPLv3)
Classifier: Programming Language :: Python :: 3
Classifier: Programming Language :: Python :: 3 :: Only
Classifier: Programming Language :: Python :: 3.5
Classifier: Programming Language :: Python :: 3.6
Classifier: Programming Language :: Python :: 3.7
Classifier: Programming Language :: Python :: 3.8
Classifier: Programming Language :: Python :: 3.9
License-File: LICENSE
Requires-Dist: mako
Requires-Dist: pygments
Requires-Dist: requests
Requires-Dist: lzstr>=0.0.3
Requires-Dist: pysvgedit>=0.0.3
